minimax/__init__.py
minimax/base_client.py
minimax/client.py
minimax/exceptions.py
minimax/types.py
minimax/utils.py
minimax_python-0.1.1.dist-info/METADATA
minimax_python-0.1.1.dist-info/WHEEL
minimax_python-0.1.1.dist-info/licenses/LICENSE
minimax_python-0.1.1.dist-info/RECORD
