Metadata-Version: 2.4
Name: minimax-python
Version: 0.1.1
Summary: Unofficial Python library for the Minimax REST API
Project-URL: Homepage, https://github.com/jesuscopado/minimax-python
Project-URL: Documentation, https://github.com/jesuscopado/minimax-python#readme
Project-URL: Repository, https://github.com/jesuscopado/minimax-python.git
Project-URL: Issues, https://github.com/jesuscopado/minimax-python/issues
Author-email: Jesús Copado <copado.je@gmail.com>
License: MIT
License-File: LICENSE
Keywords: ai,ai-video-generation,api,generation,minimax,sdk,video
Classifier: Development Status :: 4 - Beta
Classifier: Intended Audience :: Developers
Classifier: License :: OSI Approved :: MIT License
Classifier: Programming Language :: Python :: 3
Classifier: Programming Language :: Python :: 3.8
Classifier: Programming Language :: Python :: 3.9
Classifier: Programming Language :: Python :: 3.10
Classifier: Programming Language :: Python :: 3.11
Classifier: Topic :: Software Development :: Libraries :: Python Modules
Requires-Python: >=3.8
Requires-Dist: httpx>=0.24.0
Requires-Dist: pydantic>=2.0.0
Requires-Dist: python-dotenv>=1.0.1
Provides-Extra: dev
Requires-Dist: black>=23.0.0; extra == 'dev'
Requires-Dist: build>=1.0.0; extra == 'dev'
Requires-Dist: mypy>=1.0.0; extra == 'dev'
Requires-Dist: pytest-asyncio>=0.21.0; extra == 'dev'
Requires-Dist: pytest>=7.0.0; extra == 'dev'
Requires-Dist: ruff>=0.0.290; extra == 'dev'
Requires-Dist: twine>=4.0.0; extra == 'dev'
